[{"date":"Fri, 23 Jul 2021 10:15:57 GMT","sloc":75,"lloc":26,"functions":4,"deliveredBugs":0.263,"maintainability":68.517,"lintErrors":8,"difficulty":16.75},{"date":"Fri, 23 Jul 2021 10:40:34 GMT","sloc":75,"lloc":26,"functions":4,"deliveredBugs":0.263,"maintainability":68.517,"lintErrors":8,"difficulty":16.75},{"date":"Fri, 23 Jul 2021 11:18:46 GMT","sloc":75,"lloc":26,"functions":4,"deliveredBugs":0.263,"maintainability":68.517,"lintErrors":8,"difficulty":16.75},{"date":"Fri, 23 Jul 2021 11:53:43 GMT","sloc":75,"lloc":26,"functions":4,"deliveredBugs":0.263,"maintainability":68.517,"lintErrors":5,"difficulty":16.75},{"date":"Fri, 23 Jul 2021 11:55:42 GMT","sloc":75,"lloc":26,"functions":4,"deliveredBugs":0.263,"maintainability":68.517,"lintErrors":5,"difficulty":16.75}]